AUTHORS
LICENSE
README.rst
setup.cfg
setup.py
bose/__init__.py
bose/account_generator.py
bose/analytics.py
bose/base_data.py
bose/base_task.py
bose/beep_utils.py
bose/bose_driver.py
bose/bose_driver_selenium_wire.py
bose/bose_undetected_driver.py
bose/create_driver.py
bose/download_driver.py
bose/ip_utils.py
bose/launch_tasks.py
bose/local_storage.py
bose/local_storage_driver.py
bose/opponent.py
bose/output.py
bose/profile.py
bose/schedule_utils.py
bose/task_config.py
bose/task_info.py
bose/temp_mail.py
bose/user_agent.py
bose/utils.py
bose/wait.py
bose/window_size.py
bose.egg-info/PKG-INFO
bose.egg-info/SOURCES.txt
bose.egg-info/dependency_links.txt
bose.egg-info/requires.txt
bose.egg-info/top_level.txt