Metadata-Version: 2.1
Name: bose
Version: 2.0.22
Summary: The Ultimate Web Scraping Framework
Author: Chetan Jain
Author-email: chetan@omkar.cloud
Maintainer: Chetan Jain
Maintainer-email: chetan@omkar.cloud
License: MIT
Project-URL: Documentation, https://omkar.cloud/bose/
Project-URL: Source, https://github.com/omkarcloud/bose
Project-URL: Tracker, https://github.com/omkarcloud/bose/issues
Keywords: crawler,framework,scraping,crawling,web-scraping,web-scraping-python,cloudflare-bypass,anti-detection,bot-detection,automation,webdriver,browser
Classifier: Framework :: Scrapy
Classifier: Development Status :: 5 - Production/Stable
Classifier: Environment :: Console
Classifier: Intended Audience :: Developers
Classifier: License :: OSI Approved :: MIT License
Classifier: Operating System :: OS Independent
Classifier: Programming Language :: Python
Classifier: Programming Language :: Python :: 3
Classifier: Programming Language :: Python :: 3.7
Classifier: Programming Language :: Python :: 3.8
Classifier: Programming Language :: Python :: 3.9
Classifier: Programming Language :: Python :: 3.10
Classifier: Programming Language :: Python :: 3.11
Classifier: Programming Language :: Python :: Implementation :: CPython
Classifier: Programming Language :: Python :: Implementation :: PyPy
Classifier: Topic :: Internet :: WWW/HTTP
Classifier: Topic :: Software Development :: Libraries :: Application Frameworks
Classifier: Topic :: Software Development :: Libraries :: Python Modules
Requires-Python: >=3.7
License-File: LICENSE
License-File: AUTHORS
Requires-Dist: requests
Requires-Dist: chromedriver-autoinstaller-fix
Requires-Dist: selenium==4.5.0
Requires-Dist: undetected_chromedriver>=3.4.6
Requires-Dist: beautifulsoup4>=4.11.2
Requires-Dist: joblib==1.2.0
Requires-Dist: selenium-wire
